pipe21.py
pipe21-1.23.0.dist-info/METADATA
pipe21-1.23.0.dist-info/WHEEL
pipe21-1.23.0.dist-info/top_level.txt
pipe21-1.23.0.dist-info/RECORD
