Metadata-Version: 2.1
Name: pipe21
Version: 1.23.0
Summary: simple functional pipes
Author-email: Alexander Rodionov <tandav@tandav.me>
Project-URL: source, https://github.com/tandav/pipe21
Project-URL: docs, https://tandav.github.io/pipe21/
Project-URL: issues, https://github.com/tandav/pipe21/issues
Project-URL: release notes, https://github.com/tandav/pipe21/releases
Requires-Python: >=3.8
Provides-Extra: dev
Requires-Dist: bumpver ; extra == 'dev'
Requires-Dist: pre-commit ; extra == 'dev'
Requires-Dist: hypothesis ; extra == 'dev'
Requires-Dist: pytest ; extra == 'dev'
Requires-Dist: mkdocs ; extra == 'dev'
Requires-Dist: mkdocs-material ; extra == 'dev'
